jupyter_rtc_test/__init__.py
jupyter_rtc_test/__main__.py
jupyter_rtc_test/_version.py
jupyter_rtc_test/application.py
jupyter_rtc_test/handlers.py
jupyter_rtc_test/thread.py
jupyter_rtc_test/echo/__init__.py
jupyter_rtc_test/echo/handler.py
jupyter_rtc_test/relay/__init__.py
jupyter_rtc_test/relay/handler.py
jupyter_rtc_test/rtc1/__init__.py
jupyter_rtc_test/rtc1/handlers.py
jupyter_rtc_test/rtc1/loaders.py
jupyter_rtc_test/rtc1/rooms.py
jupyter_rtc_test/rtc1/stores.py
jupyter_rtc_test/rtc1/utils.py
jupyter_rtc_test/rtc1/websocketserver.py
jupyter_rtc_test/rtc2/__init__.py
jupyter_rtc_test/rtc2/collaboration.py
jupyter_rtc_test/rtc2/db.py
jupyter_rtc_test/rtc2/handler.py
jupyter_rtc_test/rtc2/messages.py
jupyter_rtc_test/static/README.md
jupyter_rtc_test/static/main.jupyterRtcTest.js
jupyter_rtc_test/stresser/__init__.py
jupyter_rtc_test/stresser/handler.py
jupyter_rtc_test/templates/index.html
jupyter_rtc_test/tests/__init__.py
jupyter_rtc_test/tests/jupyter_server_fixtures.py
jupyter_rtc_test/tests/utils.py
jupyter_rtc_test/tests/l0_yjs/__init__.py
jupyter_rtc_test/tests/l0_yjs/test_yjs.py
jupyter_rtc_test/tests/l1_yrs/__init__.py
jupyter_rtc_test/tests/l1_yrs/test_yrs.py
jupyter_rtc_test/tests/l2_ywasm/__init__.py
jupyter_rtc_test/tests/l2_ywasm/test_ywasm.py
jupyter_rtc_test/tests/l3_ypy/__init__.py
jupyter_rtc_test/tests/l3_ypy/test_ypy_array.py
jupyter_rtc_test/tests/l3_ypy/test_ypy_asyncio.py
jupyter_rtc_test/tests/l3_ypy/test_ypy_conversion.py
jupyter_rtc_test/tests/l3_ypy/test_ypy_doc.py
jupyter_rtc_test/tests/l3_ypy/test_ypy_map.py
jupyter_rtc_test/tests/l3_ypy/test_ypy_thread.py
jupyter_rtc_test/tests/l3_ypy/test_ypy_transaction.py
jupyter_rtc_test/tests/l3_ypy/test_ypy_updates.py
jupyter_rtc_test/tests/l3_ypy/test_ypy_xml.py
jupyter_rtc_test/tests/l4_ypy_store/__init__.py
jupyter_rtc_test/tests/l4_ypy_store/test_ypy_store.py
jupyter_rtc_test/tests/l4_ypy_store/utils.py
jupyter_rtc_test/tests/l5_ypy_websocket/__init__.py
jupyter_rtc_test-0.0.4.dist-info/METADATA
jupyter_rtc_test-0.0.4.dist-info/WHEEL
jupyter_rtc_test-0.0.4.dist-info/entry_points.txt
jupyter_rtc_test-0.0.4.dist-info/licenses/LICENSE
jupyter_rtc_test-0.0.4.dist-info/RECORD
